pyhmmer/CMakeLists.txt
pyhmmer/__init__.py
pyhmmer/_getid.pxi
pyhmmer/_version.py
pyhmmer/daemon.cpython-39-x86_64-linux-gnu.so
pyhmmer/daemon.pxd
pyhmmer/daemon.pyi
pyhmmer/daemon.pyx
pyhmmer/easel.cpython-39-x86_64-linux-gnu.so
pyhmmer/easel.pxd
pyhmmer/easel.pyi
pyhmmer/easel.pyx
pyhmmer/errors.cpython-39-x86_64-linux-gnu.so
pyhmmer/errors.pyi
pyhmmer/errors.pyx
pyhmmer/exceptions.pxi
pyhmmer/plan7.cpython-39-x86_64-linux-gnu.so
pyhmmer/plan7.pxd
pyhmmer/plan7.pyi
pyhmmer/plan7.pyx
pyhmmer/py.typed
pyhmmer/utils.py
pyhmmer/fileobj/__init__.pxd
pyhmmer/fileobj/bsd.h
pyhmmer/fileobj/bsd.pxd
pyhmmer/fileobj/linux.h
pyhmmer/fileobj/linux.pxd
pyhmmer/fileobj/util.h
pyhmmer/hmmer/__init__.py
pyhmmer/hmmer/_base.py
pyhmmer/hmmer/_hmmalign.py
pyhmmer/hmmer/_hmmpress.py
pyhmmer/hmmer/_hmmscan.py
pyhmmer/hmmer/_hmmsearch.py
pyhmmer/hmmer/_jackhmmer.py
pyhmmer/hmmer/_nhmmer.py
pyhmmer/hmmer/_phmmer.py
pyhmmer/reexports/__init__.pxd
pyhmmer/reexports/esl_sqio_ascii.h
pyhmmer/reexports/esl_sqio_ascii.pxd
pyhmmer/reexports/p7_hmmfile.h
pyhmmer/reexports/p7_hmmfile.pxd
pyhmmer/reexports/p7_tophits.h
pyhmmer/reexports/p7_tophits.pxd
pyhmmer/tests/__init__.py
pyhmmer/tests/requirements.txt
pyhmmer/tests/test_doctest.py
pyhmmer/tests/test_errors.py
pyhmmer/tests/test_hmmer.py
pyhmmer/tests/utils.py
pyhmmer/tests/data/README.md
pyhmmer/tests/data/hmms/make.sh
pyhmmer/tests/data/hmms/bin/PF02826.h3m
pyhmmer/tests/data/hmms/bin/PKSI-AT.h3m
pyhmmer/tests/data/hmms/bin/RF00001.h3m
pyhmmer/tests/data/hmms/bin/RREFam.h3m
pyhmmer/tests/data/hmms/bin/Thioesterase.h3m
pyhmmer/tests/data/hmms/db/PF02826.hmm
pyhmmer/tests/data/hmms/db/PF02826.hmm.h3f
pyhmmer/tests/data/hmms/db/PF02826.hmm.h3i
pyhmmer/tests/data/hmms/db/PF02826.hmm.h3m
pyhmmer/tests/data/hmms/db/PF02826.hmm.h3p
pyhmmer/tests/data/hmms/db/PKSI-AT.hmm
pyhmmer/tests/data/hmms/db/PKSI-AT.hmm.h3f
pyhmmer/tests/data/hmms/db/PKSI-AT.hmm.h3i
pyhmmer-0.11.4.dist-info/METADATA
pyhmmer-0.11.4.dist-info/WHEEL
pyhmmer-0.11.4.dist-info/RECORD
pyhmmer-0.11.4.dist-info/licenses/COPYING
