Metadata-Version: 2.2
Name: pyhmmer
Version: 0.11.4
Summary: Cython bindings and Python interface to HMMER3.
Keywords: bioinformatics,profile,HMM,sequence,pfam
Author-Email: Martin Larralde <martin.larralde@embl.de>
License: MIT License
Classifier: Development Status :: 4 - Beta
Classifier: Intended Audience :: Developers
Classifier: Intended Audience :: Science/Research
Classifier: License :: OSI Approved :: MIT License
Classifier: Operating System :: POSIX
Classifier: Programming Language :: C
Classifier: Programming Language :: Cython
Classifier: Programming Language :: Python :: 3.7
Classifier: Programming Language :: Python :: 3.8
Classifier: Programming Language :: Python :: 3.9
Classifier: Programming Language :: Python :: 3.10
Classifier: Programming Language :: Python :: 3.11
Classifier: Programming Language :: Python :: 3.12
Classifier: Programming Language :: Python :: 3.13
Classifier: Programming Language :: Python :: 3.14
Classifier: Programming Language :: Python :: Implementation :: CPython
Classifier: Programming Language :: Python :: Implementation :: PyPy
Classifier: Topic :: Scientific/Engineering :: Bio-Informatics
Classifier: Topic :: Scientific/Engineering :: Medical Science Apps.
Classifier: Typing :: Typed
Project-URL: Documentation, https://pyhmmer.readthedocs.io/en/stable/
Project-URL: Bug Tracker, https://github.com/althonos/pyhmmer/issues
Project-URL: Changelog, https://github.com/althonos/pyhmmer/blob/master/CHANGELOG.md
Project-URL: Coverage, https://codecov.io/gh/althonos/pyhmmer/
Project-URL: Builds, https://github.com/althonos/pyhmmer/actions
Project-URL: Paper, https://doi.org/10.1093/bioinformatics/btad214
Project-URL: PyPI, https://pypi.org/project/pyhmmer
Project-URL: PiWheels, https://piwheels.org/project/pyhmmer/
Requires-Python: >=3.7
Requires-Dist: psutil<8.0,>=5.0; python_version >= "3.9"
Requires-Dist: psutil<7.0,>=5.0; python_version <= "3.8"
Provides-Extra: test
Requires-Dist: importlib-resources; python_version < "3.9" and extra == "test"
